[{"name": "assakok_6", "type": 0, "list_return": null, "nombre_user": 0, "node_user_user": [{"name": "assakok_6", "type": 1, "list_return": ["assakok_7", "assakok_7", "YGuichaoua", "tweetsintheME", "YGuichaoua", "tweetsintheME", "thiernobaz", "SaharaRebelle", "AssikAg", "issalan_", "issalan_", "issalan_", "issalan_", "issalan_", "RFI", "issalan_", "Tintintinho", "SimNasr", "Tintintinho", "SimNasr", "Tintintinho", "RFIAfrique", "malimanie"], "nombre_user": 23}, {"name": "assakok_7", "type": 1, "list_return": [], "nombre_user": 0}, {"name": "assakok_7", "type": 1, "list_return": [], "nombre_user": 0}, {"name": "YGuichaoua", "type": 1, "list_return": ["Mediapart", "J_LuengoCabrera", "denis_tull", "UN_MINUSMA", "LBenabdallah", "francoisriweb", "MENASTREAM", "MSF_WestAfrica", "MSF"], "nombre_user": 9}, {"name": "tweetsintheME", "type": 1, "list_return": ["azelin", "NickBryantNY", "Marsattaqueblog", "Marsattaqueblog", "wesleysmorgan", "hahellyer", "CMC_Cambridge", "J_LuengoCabrera", "CrisisGroup", "thiamm", "speechboy71", "jenn_ruth", "blondearabist", "jpurce", "jpurce"], "nombre_user": 15}, {"name": "YGuichaoua", "type": 1, "list_return": ["Mediapart", "J_LuengoCabrera", "denis_tull", "UN_MINUSMA", "LBenabdallah", "francoisriweb", "MENASTREAM", "MSF_WestAfrica", "MSF"], "nombre_user": 9}, {"name": "tweetsintheME", "type": 1, "list_return": ["azelin", "NickBryantNY", "Marsattaqueblog", "Marsattaqueblog", "wesleysmorgan", "hahellyer", "CMC_Cambridge", "J_LuengoCabrera", "CrisisGroup", "thiamm", "speechboy71", "jenn_ruth", "blondearabist", "jpurce", "jpurce"], "nombre_user": 15}, {"name": "thiernobaz", "type": 1, "list_return": ["Abtoure1", "Labtmltd", "Abtoure1", "IBK_DEGAGE", "AMT_ML", "ocisse691", "SBoubeye", "IBK_PRMALI", "Labtmltd", "AMT_ML", "boubou_le_prof", "ocisse691", "boubou_le_prof", "ocisse691", "AMT_ML", "boubou_le_prof", "ocisse691", "ocisse691", "thiernobaz", "boubou_le_prof", "StudioTamani", "boubou_le_prof", "boubou_le_prof", "moud223", "thiernobaz", "GouvMali", "moud223", "GouvMali", "inboraghan", "moud223", "GouvMali", "GouvMali", "amicamara95", "d1a8y", "boubou_le_prof", "baradjiper_sni", "MoulayeBakar", "moud223", "diarra_gazza", "Sirkonate", "Bambakeleti", "alysangare", "spiko_warrior", "molarchie_998", "PrincinhoDiallo", "AmadouSang", "OusmaneMakaveli", "Awbissimillah", "sadioclbly", "Broslas"], "nombre_user": 50}, {"name": "SaharaRebelle", "type": 1, "list_return": ["maliactu", "maliactu", "Mondafrique", "Mondafrique", "Mondafrique"], "nombre_user": 5}, {"name": "AssikAg", "type": 1, "list_return": [], "nombre_user": 0}, {"name": "issalan_", "type": 1, "list_return": ["libe", "Sahel_Intel", "ag_anara", "YouTube", "MoussaAgAssarid", "Walid65194000", "MENASTREAM", "FAMa_Mali", "ag_acherif", "OuestFrance", "ludilani"], "nombre_user": 11}, {"name": "issalan_", "type": 1, "list_return": ["libe", "Sahel_Intel", "ag_anara", "YouTube", "MoussaAgAssarid", "Walid65194000", "MENASTREAM", "FAMa_Mali", "ag_acherif", "OuestFrance", "ludilani"], "nombre_user": 11}, {"name": "issalan_", "type": 1, "list_return": ["libe", "Sahel_Intel", "ag_anara", "YouTube", "MoussaAgAssarid", "Walid65194000", "MENASTREAM", "FAMa_Mali", "ag_acherif", "OuestFrance", "ludilani"], "nombre_user": 11}, {"name": "issalan_", "type": 1, "list_return": ["libe", "Sahel_Intel", "ag_anara", "YouTube", "MoussaAgAssarid", "Walid65194000", "MENASTREAM", "FAMa_Mali", "ag_acherif", "OuestFrance", "ludilani"], "nombre_user": 11}, {"name": "issalan_", "type": 1, "list_return": ["libe", "Sahel_Intel", "ag_anara", "YouTube", "MoussaAgAssarid", "Walid65194000", "MENASTREAM", "FAMa_Mali", "ag_acherif", "OuestFrance", "ludilani"], "nombre_user": 11}, {"name": "RFI", "type": 1, "list_return": ["AlorsOnDitQuoi", "RFI"], "nombre_user": 2}, {"name": "issalan_", "type": 1, "list_return": ["libe", "Sahel_Intel", "ag_anara", "YouTube", "MoussaAgAssarid", "Walid65194000", "MENASTREAM", "FAMa_Mali", "ag_acherif", "OuestFrance", "ludilani"], "nombre_user": 11}, {"name": "Tintintinho", "type": 1, "list_return": ["nanguila", "Noko_Bruce", "Ouladslaymane", "ArnaudContreras", "ArnaudContreras", "Noko_Bruce", "JNMartiICRC", "Noko_Bruce", "Walid6519", "YGuichaoua", "Ouladslaymane", "RSaviozCICR", "ICRC_Africa", "AFD_France", "EtatMajorFR", "PYoussefICRC", "expertisefrance", "fabienoff", "EucapSahelMali", "FAMa_Mali", "FAMa_Mali", "FAMa_Mali", "EucapSahelMali", "FAMa_Mali", "RudyAtallah", "Kommandant_JVC", "ningari57", "nanguila", "libe"], "nombre_user": 29}, {"name": "SimNasr", "type": 1, "list_return": ["GuyVanVlierden", "SimNasr", "SimNasr", "RadioTeleSuisse", "Pas2QuartierF24", "SimNasr", "France24_ar", "RadioTeleSuisse", "k_asaad_hurr", "France24_ar", "France24_ar", "SimNasr", "naaazalkha", "France24_fr", "ToreRHamming", "Pas2QuartierF24", "UrgentF24", "fabientormos", "ChronoFil", "France24", "julienfanciulli", "France24_fr", "SimNasr"], "nombre_user": 23}, {"name": "Tintintinho", "type": 1, "list_return": ["nanguila", "Noko_Bruce", "Ouladslaymane", "ArnaudContreras", "ArnaudContreras", "Noko_Bruce", "JNMartiICRC", "Noko_Bruce", "Walid6519", "YGuichaoua", "Ouladslaymane", "RSaviozCICR", "ICRC_Africa", "AFD_France", "EtatMajorFR", "PYoussefICRC", "expertisefrance", "fabienoff", "EucapSahelMali", "FAMa_Mali", "FAMa_Mali", "FAMa_Mali", "EucapSahelMali", "FAMa_Mali", "RudyAtallah", "Kommandant_JVC", "ningari57", "nanguila", "libe"], "nombre_user": 29}, {"name": "SimNasr", "type": 1, "list_return": ["GuyVanVlierden", "SimNasr", "SimNasr", "RadioTeleSuisse", "Pas2QuartierF24", "SimNasr", "France24_ar", "RadioTeleSuisse", "k_asaad_hurr", "France24_ar", "France24_ar", "SimNasr", "naaazalkha", "France24_fr", "ToreRHamming", "Pas2QuartierF24", "UrgentF24", "fabientormos", "ChronoFil", "France24", "julienfanciulli", "France24_fr", "SimNasr"], "nombre_user": 23}, {"name": "Tintintinho", "type": 1, "list_return": ["nanguila", "Noko_Bruce", "Ouladslaymane", "ArnaudContreras", "ArnaudContreras", "Noko_Bruce", "JNMartiICRC", "Noko_Bruce", "Walid6519", "YGuichaoua", "Ouladslaymane", "RSaviozCICR", "ICRC_Africa", "AFD_France", "EtatMajorFR", "PYoussefICRC", "expertisefrance", "fabienoff", "EucapSahelMali", "FAMa_Mali", "FAMa_Mali", "FAMa_Mali", "EucapSahelMali", "FAMa_Mali", "RudyAtallah", "Kommandant_JVC", "ningari57", "nanguila", "libe"], "nombre_user": 29}, {"name": "RFIAfrique", "type": 1, "list_return": [], "nombre_user": 0}, {"name": "malimanie", "type": 1, "list_return": ["AdamAKMalle", "DicoTraore", "AdamAKMalle", "DicoTraore", "AminataSimpara1", "DicoTraore", "AdamAKMalle", "AminataSimpara1", "DicoTraore", "AdamAKMalle", "DicoTraore", "DicoTraore", "AminataSimpara1", "DicoTraore", "salimatatogora", "SBoubeye", "Symps", "DicoTraore", "malimanie", "AminataSimpara1", "wordpressdotcom"], "nombre_user": 21}], "node_user_hast": [{"name": "assakok_6", "type": 2, "list_return": ["Azawad", "Azawad", "Mali", "CJA", "AI", "Azawad", "Mali", "Azawad", "Mali", "Tin_Buktu", "Taoudeni", "Azawad", "Mali", "Sahel", "Touareg", "Azawad", "Azawad", "Fran", "Boghassa", "Kidal", "Azawad", "Mali", "Boni", "Mondoro", "Douentza", "Kidal", "Azawad", "Forgho", "Gawa"], "nombre_user": 29}, {"name": "assakok_7", "type": 2, "list_return": [], "nombre_user": 0}, {"name": "assakok_7", "type": 2, "list_return": [], "nombre_user": 0}, {"name": "YGuichaoua", "type": 2, "list_return": ["Menaka", "Mangaize", "Niger", "UNHCR", "Mali", "Burkina", "Mali", "JNIM", "Niger", "Tillabery", "Bankass", "Mali", "Mali", "G5Sahel", "Niger", "migrants", "Algeria"], "nombre_user": 17}, {"name": "tweetsintheME", "type": 2, "list_return": [], "nombre_user": 0}, {"name": "YGuichaoua", "type": 2, "list_return": ["Menaka", "Mangaize", "Niger", "UNHCR", "Mali", "Burkina", "Mali", "JNIM", "Niger", "Tillabery", "Bankass", "Mali", "Mali", "G5Sahel", "Niger", "migrants", "Algeria"], "nombre_user": 17}, {"name": "tweetsintheME", "type": 2, "list_return": [], "nombre_user": 0}, {"name": "thiernobaz", "type": 2, "list_return": [], "nombre_user": 0}, {"name": "SaharaRebelle", "type": 2, "list_return": ["Mali", "Mali", "Azawad", "Ber", "MNLA", "Foyta", "CMA", "France", "Mali", "Tombouctou", "Azawad", "Touareg", "Niger", "Azawad", "Tombouctou", "CMA", "Mali"], "nombre_user": 17}, {"name": "AssikAg", "type": 2, "list_return": [], "nombre_user": 0}, {"name": "issalan_", "type": 2, "list_return": ["Azawad", "Inahina", "Gawa", "Taziwanate", "Azawad", "Kidal", "Egharghar", "Tessalit", "Azawad", "Gawa", "Mali", "Taziwanate", "Afoud", "Azawad", "Kidal", "Inaghalawass", "Tinzawatene", "Azawad", "Kidal", "Tinzawatene", "Inaghalawass", "Algerie", "Mali", "Sogoniko", "Bamako", "Mali", "Sogoniko", "Bamako", "Mali", "Mopti", "Dera", "Perna", "Konna", "Korientze", "Azawad", "Tessalit", "Amachach", "Azawad", "An", "Kidal", "Gao", "Intikouf", "Azawad", "Kidal", "Mali", "Segou", "Tientien_bougou", "Mariko", "Azawad", "Burkina", "Mali", "Azawad", "Menaka", "Inwelane", "Talatayte", "Afoud"], "nombre_user": 56}, {"name": "issalan_", "type": 2, "list_return": ["Azawad", "Inahina", "Gawa", "Taziwanate", "Azawad", "Kidal", "Egharghar", "Tessalit", "Azawad", "Gawa", "Mali", "Taziwanate", "Afoud", "Azawad", "Kidal", "Inaghalawass", "Tinzawatene", "Azawad", "Kidal", "Tinzawatene", "Inaghalawass", "Algerie", "Mali", "Sogoniko", "Bamako", "Mali", "Sogoniko", "Bamako", "Mali", "Mopti", "Dera", "Perna", "Konna", "Korientze", "Azawad", "Tessalit", "Amachach", "Azawad", "An", "Kidal", "Gao", "Intikouf", "Azawad", "Kidal", "Mali", "Segou", "Tientien_bougou", "Mariko", "Azawad", "Burkina", "Mali", "Azawad", "Menaka", "Inwelane", "Talatayte", "Afoud"], "nombre_user": 56}, {"name": "issalan_", "type": 2, "list_return": ["Azawad", "Inahina", "Gawa", "Taziwanate", "Azawad", "Kidal", "Egharghar", "Tessalit", "Azawad", "Gawa", "Mali", "Taziwanate", "Afoud", "Azawad", "Kidal", "Inaghalawass", "Tinzawatene", "Azawad", "Kidal", "Tinzawatene", "Inaghalawass", "Algerie", "Mali", "Sogoniko", "Bamako", "Mali", "Sogoniko", "Bamako", "Mali", "Mopti", "Dera", "Perna", "Konna", "Korientze", "Azawad", "Tessalit", "Amachach", "Azawad", "An", "Kidal", "Gao", "Intikouf", "Azawad", "Kidal", "Mali", "Segou", "Tientien_bougou", "Mariko", "Azawad", "Burkina", "Mali", "Azawad", "Menaka", "Inwelane", "Talatayte", "Afoud"], "nombre_user": 56}, {"name": "issalan_", "type": 2, "list_return": ["Azawad", "Inahina", "Gawa", "Taziwanate", "Azawad", "Kidal", "Egharghar", "Tessalit", "Azawad", "Gawa", "Mali", "Taziwanate", "Afoud", "Azawad", "Kidal", "Inaghalawass", "Tinzawatene", "Azawad", "Kidal", "Tinzawatene", "Inaghalawass", "Algerie", "Mali", "Sogoniko", "Bamako", "Mali", "Sogoniko", "Bamako", "Mali", "Mopti", "Dera", "Perna", "Konna", "Korientze", "Azawad", "Tessalit", "Amachach", "Azawad", "An", "Kidal", "Gao", "Intikouf", "Azawad", "Kidal", "Mali", "Segou", "Tientien_bougou", "Mariko", "Azawad", "Burkina", "Mali", "Azawad", "Menaka", "Inwelane", "Talatayte", "Afoud"], "nombre_user": 56}, {"name": "issalan_", "type": 2, "list_return": ["Azawad", "Inahina", "Gawa", "Taziwanate", "Azawad", "Kidal", "Egharghar", "Tessalit", "Azawad", "Gawa", "Mali", "Taziwanate", "Afoud", "Azawad", "Kidal", "Inaghalawass", "Tinzawatene", "Azawad", "Kidal", "Tinzawatene", "Inaghalawass", "Algerie", "Mali", "Sogoniko", "Bamako", "Mali", "Sogoniko", "Bamako", "Mali", "Mopti", "Dera", "Perna", "Konna", "Korientze", "Azawad", "Tessalit", "Amachach", "Azawad", "An", "Kidal", "Gao", "Intikouf", "Azawad", "Kidal", "Mali", "Segou", "Tientien_bougou", "Mariko", "Azawad", "Burkina", "Mali", "Azawad", "Menaka", "Inwelane", "Talatayte", "Afoud"], "nombre_user": 56}, {"name": "RFI", "type": 2, "list_return": [], "nombre_user": 0}, {"name": "issalan_", "type": 2, "list_return": ["Azawad", "Inahina", "Gawa", "Taziwanate", "Azawad", "Kidal", "Egharghar", "Tessalit", "Azawad", "Gawa", "Mali", "Taziwanate", "Afoud", "Azawad", "Kidal", "Inaghalawass", "Tinzawatene", "Azawad", "Kidal", "Tinzawatene", "Inaghalawass", "Algerie", "Mali", "Sogoniko", "Bamako", "Mali", "Sogoniko", "Bamako", "Mali", "Mopti", "Dera", "Perna", "Konna", "Korientze", "Azawad", "Tessalit", "Amachach", "Azawad", "An", "Kidal", "Gao", "Intikouf", "Azawad", "Kidal", "Mali", "Segou", "Tientien_bougou", "Mariko", "Azawad", "Burkina", "Mali", "Azawad", "Menaka", "Inwelane", "Talatayte", "Afoud"], "nombre_user": 56}, {"name": "Tintintinho", "type": 2, "list_return": ["DIH", "Islam", "Sahel", "Bamako", "Bombou", "Mali", "Mali", "Peulh", "Canada", "Barkhane"], "nombre_user": 10}, {"name": "SimNasr", "type": 2, "list_return": ["Syria", "IslamicState", "Belgium", "Maroc", "Maroc", "Syrie", "HTS", "Idelb", "AlQaeda", "HTS", "Syrie", "HTS", "UK", "Idleb", "Syrie", "HTS", "Idelb", "AlQaeda", "Turquie", "Syrie", "HTS", "Idelb", "AlQaeda"], "nombre_user": 23}, {"name": "Tintintinho", "type": 2, "list_return": ["DIH", "Islam", "Sahel", "Bamako", "Bombou", "Mali", "Mali", "Peulh", "Canada", "Barkhane"], "nombre_user": 10}, {"name": "SimNasr", "type": 2, "list_return": ["Syria", "IslamicState", "Belgium", "Maroc", "Maroc", "Syrie", "HTS", "Idelb", "AlQaeda", "HTS", "Syrie", "HTS", "UK", "Idleb", "Syrie", "HTS", "Idelb", "AlQaeda", "Turquie", "Syrie", "HTS", "Idelb", "AlQaeda"], "nombre_user": 23}, {"name": "Tintintinho", "type": 2, "list_return": ["DIH", "Islam", "Sahel", "Bamako", "Bombou", "Mali", "Mali", "Peulh", "Canada", "Barkhane"], "nombre_user": 10}, {"name": "RFIAfrique", "type": 2, "list_return": [], "nombre_user": 0}, {"name": "malimanie", "type": 2, "list_return": ["Afrique", "Afrique", "Mali", "Mali"], "nombre_user": 4}], "node_hast_user": [{"name": "Azawad", "type": 1, "list_return": ["ALIUF", "Aghanibe", "Aghanibe", "Inkinane3", "ALIUF", "shariffofo845", "ALIUF", "amacharoudj", "malikth8geek", "LeilaBeratto", "ze_boris", "ibrahim_ag_lpt", "ibrahim_ag_lpt", "ibrahim_ag_lpt", "bibSanhadja", "GirlGhost2030", "Inkinane1", "Aghanibe"], "nombre_user": 18}, {"name": "Azawad", "type": 1, "list_return": ["ALIUF", "Aghanibe", "Aghanibe", "Inkinane3", "ALIUF", "shariffofo845", "ALIUF", "amacharoudj", "malikth8geek", "LeilaBeratto", "ze_boris", "ibrahim_ag_lpt", "ibrahim_ag_lpt", "ibrahim_ag_lpt", "bibSanhadja", "GirlGhost2030", "Inkinane1", "Aghanibe"], "nombre_user": 18}, {"name": "Mali", "type": 1, "list_return": ["MENASTREAM", "GBajj", "JigiAfrica", "MENASTREAM", "MeNotreally", "CanadaFP", "ASFCanada", "CVJR_MALI", "LGaladza", "gsrescueelite", "giddings3_g", "gsrescueelite", "claire_62", "sonietamb", "SaluaElomari", "BenbereM", "Abtoure1", "AMT_ML", "WorldBank", "Donilab1", "bbclysedoucet", "PMaurerICRC", "david_colquhoun", "AMT_ML", "thiamastousow", "BenbereM", "Nbeng_franck", "bbclysedoucet", "PMaurerICRC", "thewhirlinzim", "bbclysedoucet", "imagic", "marciakimwong", "PMaurerICRC", "annemoirab"], "nombre_user": 35}, {"name": "CJA", "type": 1, "list_return": ["FerLopeez98", "LFosatti", "CristianAbanCJA", "CJA_Journal", "khas01", "CJA_Journal", "_kmisha_", "CJA_Journal", "michaelhongo", "CJAOficial", "GraLaProdu", "CJAOficial", "MatiasDaherCJA", "CJAOficial", "rumboascenso929", "CJAOficial", "angelportezuelo", "CJAOficial", "DanielGColque", "CJAOficial", "DanielGColque", "CJAOficial", "YeyuOntiveros", "CJAOficial", "YeyuOntiveros"], "nombre_user": 25}, {"name": "AI", "type": 1, "list_return": ["danielnewmanUV", "theChrisChua", "SpirosMargaris", "theChrisChua", "SpirosMargaris", "theChrisChua", "AmandaCosco", "YouCamApps", "goya813", "AmandaCosco", "YouCamApps", "ghost_nox", "AmandaCosco", "YouCamApps", "JaEvon_MN", "UserExperienceU", "james13431800", "HKW_Berlin", "RoamingWords", "SpirosMargaris", "SSXman2", "UserExperienceU", "tien83526070", "R_Demidchuk", "ifrodriguezm81", "Earnix_Inc", "MarkStoutMedia", "Ad_World_Today", "armaninspace", "khan_hanzla", "AmandaCosco", "YouCamApps", "RichardTunley"], "nombre_user": 33}, {"name": "Azawad", "type": 1, "list_return": ["ALIUF", "Aghanibe", "Aghanibe", "Inkinane3", "ALIUF", "shariffofo845", "ALIUF", "amacharoudj", "malikth8geek", "LeilaBeratto", "ze_boris", "ibrahim_ag_lpt", "ibrahim_ag_lpt", "ibrahim_ag_lpt", "bibSanhadja", "GirlGhost2030", "Inkinane1", "Aghanibe"], "nombre_user": 18}, {"name": "Mali", "type": 1, "list_return": ["MENASTREAM", "GBajj", "JigiAfrica", "MENASTREAM", "MeNotreally", "CanadaFP", "ASFCanada", "CVJR_MALI", "LGaladza", "gsrescueelite", "giddings3_g", "gsrescueelite", "claire_62", "sonietamb", "SaluaElomari", "BenbereM", "Abtoure1", "AMT_ML", "WorldBank", "Donilab1", "bbclysedoucet", "PMaurerICRC", "david_colquhoun", "AMT_ML", "thiamastousow", "BenbereM", "Nbeng_franck", "bbclysedoucet", "PMaurerICRC", "thewhirlinzim", "bbclysedoucet", "imagic", "marciakimwong", "PMaurerICRC", "annemoirab"], "nombre_user": 35}, {"name": "Azawad", "type": 1, "list_return": ["ALIUF", "Aghanibe", "Aghanibe", "Inkinane3", "ALIUF", "shariffofo845", "ALIUF", "amacharoudj", "malikth8geek", "LeilaBeratto", "ze_boris", "ibrahim_ag_lpt", "ibrahim_ag_lpt", "ibrahim_ag_lpt", "bibSanhadja", "GirlGhost2030", "Inkinane1", "Aghanibe"], "nombre_user": 18}, {"name": "Mali", "type": 1, "list_return": ["MENASTREAM", "GBajj", "JigiAfrica", "MENASTREAM", "MeNotreally", "CanadaFP", "ASFCanada", "CVJR_MALI", "LGaladza", "gsrescueelite", "giddings3_g", "gsrescueelite", "claire_62", "sonietamb", "SaluaElomari", "BenbereM", "Abtoure1", "AMT_ML", "WorldBank", "Donilab1", "bbclysedoucet", "PMaurerICRC", "david_colquhoun", "AMT_ML", "thiamastousow", "BenbereM", "Nbeng_franck", "bbclysedoucet", "PMaurerICRC", "thewhirlinzim", "bbclysedoucet", "imagic", "marciakimwong", "PMaurerICRC", "annemoirab"], "nombre_user": 35}, {"name": "Tin_Buktu", "type": 1, "list_return": [], "nombre_user": 0}, {"name": "Taoudeni", "type": 1, "list_return": [], "nombre_user": 0}, {"name": "Azawad", "type": 1, "list_return": ["ALIUF", "Aghanibe", "Aghanibe", "Inkinane3", "ALIUF", "shariffofo845", "ALIUF", "amacharoudj", "malikth8geek", "LeilaBeratto", "ze_boris", "ibrahim_ag_lpt", "ibrahim_ag_lpt", "ibrahim_ag_lpt", "bibSanhadja", "GirlGhost2030", "Inkinane1", "Aghanibe"], "nombre_user": 18}, {"name": "Mali", "type": 1, "list_return": ["MENASTREAM", "GBajj", "JigiAfrica", "MENASTREAM", "MeNotreally", "CanadaFP", "ASFCanada", "CVJR_MALI", "LGaladza", "gsrescueelite", "giddings3_g", "gsrescueelite", "claire_62", "sonietamb", "SaluaElomari", "BenbereM", "Abtoure1", "AMT_ML", "WorldBank", "Donilab1", "bbclysedoucet", "PMaurerICRC", "david_colquhoun", "AMT_ML", "thiamastousow", "BenbereM", "Nbeng_franck", "bbclysedoucet", "PMaurerICRC", "thewhirlinzim", "bbclysedoucet", "imagic", "marciakimwong", "PMaurerICRC", "annemoirab"], "nombre_user": 35}, {"name": "Sahel", "type": 1, "list_return": ["ElvisGijap", "ToudaKaka", "G5_Sahel_SP", "SidikouMaman", "Jm", "TourePresi", "UN_UNOWAS", "TourePresi", "Sahel2R3S", "lesyeuxdumonde", "JessyPerie", "TourePresi", "laurent_bossard", "SowAmadoualisow", "5472_nde", "burkina24", "MFS001", "Tom_Antonov", "itsme_leclerc", "RussiaUN", "DJSiri", "RussiaUN", "DJSiri", "burkina24", "5472_nde", "Tom_Antonov", "martinjhurt", "laurent_bossard", "Saharien1", "Tom_Antonov", "AlbertoBueno_", "Tom_Antonov", "VahurKoorits", "Tom_Antonov", "AllaisF"], "nombre_user": 35}, {"name": "Touareg", "type": 1, "list_return": ["BlackwaterMotor", "JeTargui", "shkhs1717", "JeTargui", "2q9DQCLhG0xLlDy", "JeTargui", "malikth8geek", "JeTargui", "ytimesmotoring", "TheYorksTimes", "UKVolkswagen", "WeLuvCars", "atlautomotive", "PolokwaneVW", "MissBacheloret1", "softkaplama", "ytimesmotoring", "TheYorksTimes", "UKVolkswagen", "RosedaleLeasing", "AutoMoto_Mag", "PolokwaneVW", "MYBTumi88", "GruppoFassina", "PolokwaneVW", "OmarZeina3", "DopyDola"], "nombre_user": 27}, {"name": "Azawad", "type": 1, "list_return": ["ALIUF", "Aghanibe", "Aghanibe", "Inkinane3", "ALIUF", "shariffofo845", "ALIUF", "amacharoudj", "malikth8geek", "LeilaBeratto", "ze_boris", "ibrahim_ag_lpt", "ibrahim_ag_lpt", "ibrahim_ag_lpt", "bibSanhadja", "GirlGhost2030", "Inkinane1", "Aghanibe"], "nombre_user": 18}, {"name": "Azawad", "type": 1, "list_return": ["ALIUF", "Aghanibe", "Aghanibe", "Inkinane3", "ALIUF", "shariffofo845", "ALIUF", "amacharoudj", "malikth8geek", "LeilaBeratto", "ze_boris", "ibrahim_ag_lpt", "ibrahim_ag_lpt", "ibrahim_ag_lpt", "bibSanhadja", "GirlGhost2030", "Inkinane1", "Aghanibe"], "nombre_user": 18}, {"name": "Fran", "type": 1, "list_return": ["Thalys_Nunes", "LizAriyala", "chispitinino", "LizAriyala", "FamouslyJess", "blw9098e", "fran_nail", "blw9098e", "fran_nail", "parco_fukuoka", "pokerface_fukuP", "albanycrossfit", "franscuen", "victoria_chlz"], "nombre_user": 14}, {"name": "Boghassa", "type": 1, "list_return": [], "nombre_user": 0}, {"name": "Kidal", "type": 1, "list_return": ["UN_MINUSMA", "DiabateIssa18", "YanickToutain", "BasPhilippe", "Danhytess2", "INTERPOL_HQ", "Interpol", "INTERPOL_Cyber", "Courdecassation", "Julie_Amadis", "publicsenat", "senateursLa", "HerveDebacker", "YanickToutain", "BasPhilippe", "Danhytess2", "INTERPOL_HQ", "Interpol", "INTERPOL_Cyber", "Courdecassation", "Julie_Amadis", "publicsenat", "senateursLa", "jakherjak", "YanickToutain", "BasPhilippe", "Danhytess2", "INTERPOL_HQ", "Interpol", "INTERPOL_Cyber", "Courdecassation", "Julie_Amadis", "publicsenat", "senateursLa", "SylvieDUH", "YanickToutain", "BasPhilippe", "Danhytess2", "INTERPOL_HQ", "Interpol", "INTERPOL_Cyber", "Courdecassation", "Julie_Amadis", "publicsenat", "senateursLa", "BrigittePagne", "YanickToutain", "BasPhilippe", "Danhytess2", "INTERPOL_HQ", "Interpol", "INTERPOL_Cyber", "Courdecassation", "Julie_Amadis", "publicsenat", "senateursLaREM", "CSMagistrature", "Defense_gouv", "armeedeterre", "Armee_de_lair", "EtatMajorFR", "LaCABAT", "DRHmindef", "VIGI_MI", "Reuters", "YanickToutain", "ikeitakeita", "YanickToutain", "SabineBaudoinG", "YanickToutain", "pauloukone", "olivier_salgado", "olivier_salgado", "UN_MINUSMA", "madoukassa", "UN_MINUSMA", "SOULEYTOGOI", "DialloJulien"], "nombre_user": 78}, {"name": "Azawad", "type": 1, "list_return": ["ALIUF", "Aghanibe", "Aghanibe", "Inkinane3", "ALIUF", "shariffofo845", "ALIUF", "amacharoudj", "malikth8geek", "LeilaBeratto", "ze_boris", "ibrahim_ag_lpt", "ibrahim_ag_lpt", "ibrahim_ag_lpt", "bibSanhadja", "GirlGhost2030", "Inkinane1", "Aghanibe"], "nombre_user": 18}, {"name": "Mali", "type": 1, "list_return": ["MENASTREAM", "GBajj", "JigiAfrica", "MENASTREAM", "MeNotreally", "CanadaFP", "ASFCanada", "CVJR_MALI", "LGaladza", "gsrescueelite", "giddings3_g", "gsrescueelite", "claire_62", "sonietamb", "SaluaElomari", "BenbereM", "Abtoure1", "AMT_ML", "WorldBank", "Donilab1", "bbclysedoucet", "PMaurerICRC", "david_colquhoun", "AMT_ML", "thiamastousow", "BenbereM", "Nbeng_franck", "bbclysedoucet", "PMaurerICRC", "thewhirlinzim", "bbclysedoucet", "imagic", "marciakimwong", "PMaurerICRC", "annemoirab"], "nombre_user": 35}, {"name": "Boni", "type": 1, "list_return": ["WalidAg_M", "MedLamineOuldO1", "estanciamimosa", "estanciamimosa", "WalidAg_M", "AbouDuCompte", "halcainbow8", "a___wa______ke", "WalidAg_M", "luniseMarquis", "WalidAg_M", "PennyKDN", "WalidAg_M", "HabarOum", "WalidAg_M", "Jade_Hun", "WalidAg_M", "Abou_2ner", "WalidAg_M", "JacquesHicham", "WalidAg_M", "CookieM71720969", "WalidAg_M", "FabriceParot", "MinnieLoveMomo1", "iMe_Dreamnote", "biYRN4bCRGSYwvW", "MrPotatoDay", "biYRN4bCRGSYwvW", "WalidAg_M", "MAoufa"], "nombre_user": 31}, {"name": "Mondoro", "type": 1, "list_return": [], "nombre_user": 0}, {"name": "Douentza", "type": 1, "list_return": ["ocisse691", "SowAmadoualisow", "FAMa_Mali", "SowAmadoualisow", "SowAmadoualisow", "FAMa_Mali", "ocisse691", "ocisse691", "EtatMajorFR", "FAMa_Mali", "Arkiakiki", "ocisse691", "EtatMajorFR", "FAMa_Mali", "Salifou1", "ocisse691", "EtatMajorFR", "FAMa_Mali", "SowAmadoualisow", "ocisse691", "EtatMajorFR", "FAMa_Mali", "adam_sandor", "ocisse691", "EtatMajorFR", "FAMa_Mali", "IsselmouSalihi", "ocisse691", "EtatMajorFR", "FAMa_Mali", "LPeuls", "ocisse691", "EtatMajorFR", "FAMa_Mali", "aurelientobie", "EtatMajorFR", "FAMa_Mali", "ocisse691", "LibreSahel", "RFIAfrique", "LibreSahel", "LibreSahel", "RFIAfrique", "Gabisymen", "RFIAfrique", "LibreSahel", "ikeitakeita", "KKunafoni"], "nombre_user": 48}, {"name": "Kidal", "type": 1, "list_return": ["UN_MINUSMA", "DiabateIssa18", "YanickToutain", "BasPhilippe", "Danhytess2", "INTERPOL_HQ", "Interpol", "INTERPOL_Cyber", "Courdecassation", "Julie_Amadis", "publicsenat", "senateursLa", "HerveDebacker", "YanickToutain", "BasPhilippe", "Danhytess2", "INTERPOL_HQ", "Interpol", "INTERPOL_Cyber", "Courdecassation", "Julie_Amadis", "publicsenat", "senateursLa", "jakherjak", "YanickToutain", "BasPhilippe", "Danhytess2", "INTERPOL_HQ", "Interpol", "INTERPOL_Cyber", "Courdecassation", "Julie_Amadis", "publicsenat", "senateursLa", "SylvieDUH", "YanickToutain", "BasPhilippe", "Danhytess2", "INTERPOL_HQ", "Interpol", "INTERPOL_Cyber", "Courdecassation", "Julie_Amadis", "publicsenat", "senateursLa", "BrigittePagne", "YanickToutain", "BasPhilippe", "Danhytess2", "INTERPOL_HQ", "Interpol", "INTERPOL_Cyber", "Courdecassation", "Julie_Amadis", "publicsenat", "senateursLaREM", "CSMagistrature", "Defense_gouv", "armeedeterre", "Armee_de_lair", "EtatMajorFR", "LaCABAT", "DRHmindef", "VIGI_MI", "Reuters", "YanickToutain", "ikeitakeita", "YanickToutain", "SabineBaudoinG", "YanickToutain", "pauloukone", "olivier_salgado", "olivier_salgado", "UN_MINUSMA", "madoukassa", "UN_MINUSMA", "SOULEYTOGOI", "DialloJulien"], "nombre_user": 78}, {"name": "Azawad", "type": 1, "list_return": ["ALIUF", "Aghanibe", "Aghanibe", "Inkinane3", "ALIUF", "shariffofo845", "ALIUF", "amacharoudj", "malikth8geek", "LeilaBeratto", "ze_boris", "ibrahim_ag_lpt", "ibrahim_ag_lpt", "ibrahim_ag_lpt", "bibSanhadja", "GirlGhost2030", "Inkinane1", "Aghanibe"], "nombre_user": 18}, {"name": "Forgho", "type": 1, "list_return": [], "nombre_user": 0}, {"name": "Gawa", "type": 1, "list_return": ["ni_oldskool", "reznoviccc", "YouTube", "BATTLEFIELD", "Silly_Sunday", "ni_oldskool", "reznoviccc", "YouTube", "BATTLEFIELD", "tonic__wine69", "ni_oldskool", "reznoviccc", "YouTube", "BATTLEFIELD", "voodoochld1", "reznoviccc", "YouTube", "BATTLEFIELD", "Silly_Sunday", "ni_oldskool", "BodedernAthlet1", "fourcrossesfc_", "WelshAlliance2", "henrywinter", "piersmorgan", "ColinBrw", "acitalian", "ClixSensei", "acitalian", "NorthernIreland", "howtwoday", "BodedernAthlet1", "fourcrossesfc_", "emzbo9", "BodedernAthlet1", "fourcrossesfc_", "Cymrugroundhop1", "fourcrossesfc_", "BodedernAthlet1", "NotBrazil", "debnornirn", "BelfastFutsal", "NorthernIreland", "FutsalMalta", "CraigTaylor_11", "NotBrazil"], "nombre_user": 46}], "node_hast_hast": [{"name": "Azawad", "type": 2, "list_return": ["Azawad", "Azawad", "M", "Azawad", "Azawad", "Azawad", "Sahara_Rebelle", "Azawad", "Tombouctou", "azawad", "Sahel", "Mali", "Azawad", "Tombouctou", "Montreal", "Canada", "Sahel", "Mali", "Azawad", "Tombouctou", "Montreal", "Canada", "Touareg", "MNLA", "AZAWAD"], "nombre_user": 25}, {"name": "Azawad", "type": 2, "list_return": ["Azawad", "Azawad", "M", "Azawad", "Azawad", "Azawad", "Sahara_Rebelle", "Azawad", "Tombouctou", "azawad", "Sahel", "Mali", "Azawad", "Tombouctou", "Montreal", "Canada", "Sahel", "Mali", "Azawad", "Tombouctou", "Montreal", "Canada", "Touareg", "MNLA", "AZAWAD"], "nombre_user": 25}, {"name": "Mali", "type": 2, "list_return": ["Mali", "JNIM", "Barkhane", "FAMa", "Barkhane", "Mali", "FAMa", "BurkinaFaso", "Mali", "Mali", "Mali", "Guinea", "Marruecos", "Mali", "migrantes", "Mali", "Mali", "climatechange", "num", "Mali", "startupAct", "Mali", "Mali", "climatechange", "finally", "timbuktu", "mali", "resilience", "Mali"], "nombre_user": 29}, {"name": "CJA", "type": 2, "list_return": ["CJA", "CJA", "Jam", "103A", "CJA", "CJA", "Anesthesia", "CJA", "Y3", "F", "Amistoso", "CJA", "CN", "Futbol", "Amistoso", "CJA", "CN", "Futbol", "Amistoso", "CJA", "CN", "Futbol", "Amistoso", "CJA", "CN", "F", "Amistoso", "CJA", "CN", "Futbol", "Amistoso", "CJA", "CN", "F", "Amistoso", "CJA", "CN", "Futbol", "Amistoso", "CJA", "CN"], "nombre_user": 41}, {"name": "AI", "type": 2, "list_return": ["AI", "MachineLearning", "ArtificialIntelligence", "Disrupt", "Profession", "fintech", "insurtech", "futureofwork", "ArtificialIntelligence", "fintech", "insur", "CES2019", "SmartMirror", "AR", "AI", "CES2019", "SmartMirror", "AR", "AI", "CES2019", "SmartMirror", "AR", "AI", "Agileforbusiness", "DigitalTransformation", "EnterpriseAgilit", "DasNeueAlphabet", "TheNewAlphabet", "HKW", "DNA", "AI", "ArtificialIntelligence", "fintech", "insur", "Digital", "Transformation", "Business", "Guide", "DigitalTransformation", "EnterpriseAgility", "Consultant", "CX", "UX", "Futurist", "T", "smartcities", "insurance", "personalization", "ML", "AI", "data", "Be", "Light", "darkness", "Love", "one", "ProfessorWatts", "TeachLove", "LoveOneAnother", "AI", "BigData", "ML", "Iot", "Artificialintelligence", "Mach", "CES2019", "SmartMirror", "AR", "AI"], "nombre_user": 69}, {"name": "Azawad", "type": 2, "list_return": ["Azawad", "Azawad", "M", "Azawad", "Azawad", "Azawad", "Sahara_Rebelle", "Azawad", "Tombouctou", "azawad", "Sahel", "Mali", "Azawad", "Tombouctou", "Montreal", "Canada", "Sahel", "Mali", "Azawad", "Tombouctou", "Montreal", "Canada", "Touareg", "MNLA", "AZAWAD"], "nombre_user": 25}, {"name": "Mali", "type": 2, "list_return": ["Mali", "JNIM", "Barkhane", "FAMa", "Barkhane", "Mali", "FAMa", "BurkinaFaso", "Mali", "Mali", "Mali", "Guinea", "Marruecos", "Mali", "migrantes", "Mali", "Mali", "climatechange", "num", "Mali", "startupAct", "Mali", "Mali", "climatechange", "finally", "timbuktu", "mali", "resilience", "Mali"], "nombre_user": 29}, {"name": "Azawad", "type": 2, "list_return": ["Azawad", "Azawad", "M", "Azawad", "Azawad", "Azawad", "Sahara_Rebelle", "Azawad", "Tombouctou", "azawad", "Sahel", "Mali", "Azawad", "Tombouctou", "Montreal", "Canada", "Sahel", "Mali", "Azawad", "Tombouctou", "Montreal", "Canada", "Touareg", "MNLA", "AZAWAD"], "nombre_user": 25}, {"name": "Mali", "type": 2, "list_return": ["Mali", "JNIM", "Barkhane", "FAMa", "Barkhane", "Mali", "FAMa", "BurkinaFaso", "Mali", "Mali", "Mali", "Guinea", "Marruecos", "Mali", "migrantes", "Mali", "Mali", "climatechange", "num", "Mali", "startupAct", "Mali", "Mali", "climatechange", "finally", "timbuktu", "mali", "resilience", "Mali"], "nombre_user": 29}, {"name": "Tin_Buktu", "type": 2, "list_return": [], "nombre_user": 0}, {"name": "Taoudeni", "type": 2, "list_return": [], "nombre_user": 0}, {"name": "Azawad", "type": 2, "list_return": ["Azawad", "Azawad", "M", "Azawad", "Azawad", "Azawad", "Sahara_Rebelle", "Azawad", "Tombouctou", "azawad", "Sahel", "Mali", "Azawad", "Tombouctou", "Montreal", "Canada", "Sahel", "Mali", "Azawad", "Tombouctou", "Montreal", "Canada", "Touareg", "MNLA", "AZAWAD"], "nombre_user": 25}, {"name": "Mali", "type": 2, "list_return": ["Mali", "JNIM", "Barkhane", "FAMa", "Barkhane", "Mali", "FAMa", "BurkinaFaso", "Mali", "Mali", "Mali", "Guinea", "Marruecos", "Mali", "migrantes", "Mali", "Mali", "climatechange", "num", "Mali", "startupAct", "Mali", "Mali", "climatechange", "finally", "timbuktu", "mali", "resilience", "Mali"], "nombre_user": 29}, {"name": "Sahel", "type": 2, "list_return": ["twilight", "sunset", "fashion", "beauty", "blackbeautymatters", "african", "cameroon", "ghana", "nigeria", "sahel", "Sahel", "Sahel", "Tchad", "burkina", "Koglweogo", "Sahel", "BurkinaFaso", "Barkhane", "Sa", "Polyanskiy", "WestAfrica", "Sahel", "Sahel", "Sahel", "BurkinaFaso", "Barkhane", "Sa", "burkina", "Koglweogo", "Barkhane", "Sa", "Barkhane", "Sa", "Barkhane", "Sa"], "nombre_user": 35}, {"name": "Touareg", "type": 2, "list_return": ["Touareg", "Tiguan", "TRoc", "touareg", "touareg", "touareg", "touareg", "Tou", "VolkswagenJamaica", "Touareg", "Touareg", "VWPolokwane", "touareg", "volkswagen", "vw", "rs", "x", "mk", "car", "audi", "vwtouareg", "bnw", "golf", "s", "tdi", "v", "gti", "volkswagentouareg", "Tou", "Volkswagen", "Touareg", "AtticaCityLink", "AutoMotoGR", "Touareg", "VWPolokwane", "volkswagen", "touareg", "Touareg", "VWPolokwane", "Touareg"], "nombre_user": 40}, {"name": "Azawad", "type": 2, "list_return": ["Azawad", "Azawad", "M", "Azawad", "Azawad", "Azawad", "Sahara_Rebelle", "Azawad", "Tombouctou", "azawad", "Sahel", "Mali", "Azawad", "Tombouctou", "Montreal", "Canada", "Sahel", "Mali", "Azawad", "Tombouctou", "Montreal", "Canada", "Touareg", "MNLA", "AZAWAD"], "nombre_user": 25}, {"name": "Azawad", "type": 2, "list_return": ["Azawad", "Azawad", "M", "Azawad", "Azawad", "Azawad", "Sahara_Rebelle", "Azawad", "Tombouctou", "azawad", "Sahel", "Mali", "Azawad", "Tombouctou", "Montreal", "Canada", "Sahel", "Mali", "Azawad", "Tombouctou", "Montreal", "Canada", "Touareg", "MNLA", "AZAWAD"], "nombre_user": 25}, {"name": "Fran", "type": 2, "list_return": ["Marcio", "Fran", "Dione", "Gabi", "frannailsalon", "frannail", "fran", "nails", "winter", "daikanyama", "frannailsalon", "frannail", "fran", "nails", "winter", "propo", "FRAN", "styling", "pokerface", "teamacf", "albanycrossfit", "bebetter", "fran", "crossfit", "fran"], "nombre_user": 25}, {"name": "Boghassa", "type": 2, "list_return": [], "nombre_user": 0}, {"name": "Kidal", "type": 2, "list_return": ["PhotoduJour", "Casquesbleus", "tchad", "PhilippeBas", "LeDrian", "Mali", "Tessougu", "AhmadaAgBibi", "jihadistes", "Ansardine", "HCUA", "d", "RPM", "IBK", "Kidal", "charia", "PhilippeBas", "LeDrian", "Mali", "Tessougu", "AhmadaAgBibi", "jihadistes", "HCUA", "d", "RPM", "IBK", "Kidal", "charia", "Casquesbleus", "MINUSMA", "Kidal", "AhmadaAgBibi", "jihadistes", "Ansardine", "France", "HCUA", "charia", "Kidal", "Kidal", "Mopti", "Tombouctou", "Gao", "Kidal", "M", "S", "Kayes", "PhotoduJour", "Casquesbleus", "tchad", "PhotoduJour", "Casquesbleus", "tchad", "Mali", "tchadien", "MINUSMA", "Kidal"], "nombre_user": 56}, {"name": "Azawad", "type": 2, "list_return": ["Azawad", "Azawad", "M", "Azawad", "Azawad", "Azawad", "Sahara_Rebelle", "Azawad", "Tombouctou", "azawad", "Sahel", "Mali", "Azawad", "Tombouctou", "Montreal", "Canada", "Sahel", "Mali", "Azawad", "Tombouctou", "Montreal", "Canada", "Touareg", "MNLA", "AZAWAD"], "nombre_user": 25}, {"name": "Mali", "type": 2, "list_return": ["Mali", "JNIM", "Barkhane", "FAMa", "Barkhane", "Mali", "FAMa", "BurkinaFaso", "Mali", "Mali", "Mali", "Guinea", "Marruecos", "Mali", "migrantes", "Mali", "Mali", "climatechange", "num", "Mali", "startupAct", "Mali", "Mali", "climatechange", "finally", "timbuktu", "mali", "resilience", "Mali"], "nombre_user": 29}, {"name": "Boni", "type": 2, "list_return": ["Mopti", "Barkhane", "boni", "Mopti", "Barkhane", "DreamNote", "YOUI", "BoNi", "Lara", "MISO", "Sumin", "Eu", "Mopti", "Barkhane", "Mopti", "Barkhane", "Mopti", "Barkhane", "Mopti", "Barkhane", "Mopti", "Barkhane", "Mopti", "Barkhane", "Mopti", "Barkhane", "Mopti", "Barkhane", "DREAMNOTE", "YOUI", "BONI", "HABIN", "MISO", "DreamNote", "Dreamlike", "miso", "boni", "habin", "hanbyeol", "Mopti", "Barkhane"], "nombre_user": 41}, {"name": "Mondoro", "type": 2, "list_return": [], "nombre_user": 0}, {"name": "Douentza", "type": 2, "list_return": ["douentza", "youwarou", "douentza", "youwarou", "Mali", "Serma", "Bon", "Mali", "Serma", "Bon", "Mali", "Serma", "Bon", "Mali", "Serma", "Bon", "Mali", "Serma", "Bon", "Mali", "Serma", "Bon", "Mali", "Serma", "Bon", "Mali", "Serma", "Boni", "Douentza", "Sahel", "Mali", "op", "terroriste", "Boni", "Douentza", "Sahel", "Mali", "op", "terroriste", "Boni", "Douentza", "Sahel", "Mali", "op", "terroriste", "Boni", "Douentza", "Barkhane", "Douentza", "Boni", "Mali", "Douentza"], "nombre_user": 52}, {"name": "Kidal", "type": 2, "list_return": ["PhotoduJour", "Casquesbleus", "tchad", "PhilippeBas", "LeDrian", "Mali", "Tessougu", "AhmadaAgBibi", "jihadistes", "Ansardine", "HCUA", "d", "RPM", "IBK", "Kidal", "charia", "PhilippeBas", "LeDrian", "Mali", "Tessougu", "AhmadaAgBibi", "jihadistes", "HCUA", "d", "RPM", "IBK", "Kidal", "charia", "Casquesbleus", "MINUSMA", "Kidal", "AhmadaAgBibi", "jihadistes", "Ansardine", "France", "HCUA", "charia", "Kidal", "Kidal", "Mopti", "Tombouctou", "Gao", "Kidal", "M", "S", "Kayes", "PhotoduJour", "Casquesbleus", "tchad", "PhotoduJour", "Casquesbleus", "tchad", "Mali", "tchadien", "MINUSMA", "Kidal"], "nombre_user": 56}, {"name": "Azawad", "type": 2, "list_return": ["Azawad", "Azawad", "M", "Azawad", "Azawad", "Azawad", "Sahara_Rebelle", "Azawad", "Tombouctou", "azawad", "Sahel", "Mali", "Azawad", "Tombouctou", "Montreal", "Canada", "Sahel", "Mali", "Azawad", "Tombouctou", "Montreal", "Canada", "Touareg", "MNLA", "AZAWAD"], "nombre_user": 25}, {"name": "Forgho", "type": 2, "list_return": [], "nombre_user": 0}, {"name": "Gawa", "type": 2, "list_return": ["GAWA", "bcitw", "NeverBeTheSame", "dicefriend", "BFV", "GA", "GAWA", "porcellana", "handpainted", "porcelain", "madeinitaly", "italy", "necklace", "pendant", "goldplated", "mug", "gawa", "espresso", "coffee", "interiordesign", "weddinggift", "gift", "dubai", "shopping", "sharjah", "ajman", "alain", "oman", "usa", "iran", "saudiarabia", "regalo", "russia", "b", "porcellana", "handpainted", "porcelain", "madeinitaly", "italy", "necklace", "pendant", "goldplated", "mug", "gawa", "espresso", "coffee", "interiordesign", "weddinggift", "gift", "dubai", "shopping", "sharjah", "ajman", "alain", "oman", "usa", "iran", "saudiarabia", "regalo", "russia", "bahrain", "kuwait", "GAWA", "GA", "GA", "GAWA", "GAWA", "NIR", "gambleaware", "WhenTheFunStopsStop", "headingleyafc"], "nombre_user": 71}]}]